tablat/TabStyle.py
tablat/Table.py
tablat/__init__.py
tablat-0.2.0.dist-info/LICENSE
tablat-0.2.0.dist-info/METADATA
tablat-0.2.0.dist-info/WHEEL
tablat-0.2.0.dist-info/top_level.txt
tablat-0.2.0.dist-info/RECORD
