Metadata-Version: 2.1
Name: tablat
Version: 0.2.0
Summary: Print basic tables in python
Home-page: https://github.com/salpreh/tablat
Author: salpreh
Author-email: salva.perez46@gmail.com
License: MIT License
Platform: UNKNOWN
